pylint_t2/__init__.py
pylint_t2/graphene.py
pylint_t2-0.0.1.dist-info/LICENSE
pylint_t2-0.0.1.dist-info/METADATA
pylint_t2-0.0.1.dist-info/WHEEL
pylint_t2-0.0.1.dist-info/top_level.txt
pylint_t2-0.0.1.dist-info/RECORD
