Metadata-Version: 2.1
Name: pylint-t2
Version: 0.0.1
Summary: Transport2 pylint plugin
Home-page: https://github.com/rustemg/pylint-t2
Author: Röstäm Gazizov
Author-email: gazizov@tn.ru
License: MIT
Keywords: pylint plugin
Platform: UNKNOWN
Classifier: Development Status :: 3 - Alpha
Classifier: Intended Audience :: Developers
Classifier: Topic :: Software Development :: Libraries
Classifier: Programming Language :: Python :: 3
Classifier: License :: OSI Approved :: MIT License
Classifier: Operating System :: OS Independent
Requires-Python: >=3.6
Requires-Dist: pylint (>=2.4)
Requires-Dist: pylint-plugin-utils (>=0.6)
Provides-Extra: dev
Requires-Dist: black (==19.10b0) ; extra == 'dev'
